[
    {
        "id": "eb1ca74049e20df8",
        "type": "tab",
        "label": "Flow 5",
        "disabled": false,
        "info": "",
        "env": []
    },
    {
        "id": "065b84c9c0996259",
        "type": "mqtt out",
        "z": "eb1ca74049e20df8",
        "name": "",
        "topic": "Haus/hljod",
        "qos": "",
        "retain": "",
        "respTopic": "",
        "contentType": "",
        "userProps": "",
        "correl": "",
        "expiry": "",
        "broker": "8f94c513d5abaf60",
        "x": 530,
        "y": 240,
        "wires": []
    },
    {
        "id": "be0453c56bb42545",
        "type": "mqtt out",
        "z": "eb1ca74049e20df8",
        "name": "",
        "topic": "Vasaljos/litur",
        "qos": "",
        "retain": "",
        "respTopic": "",
        "contentType": "",
        "userProps": "",
        "correl": "",
        "expiry": "",
        "broker": "8f94c513d5abaf60",
        "x": 550,
        "y": 280,
        "wires": []
    },
    {
        "id": "92d6fdc1ac7524fa",
        "type": "mqtt out",
        "z": "eb1ca74049e20df8",
        "name": "",
        "topic": "Haus/lysa_augu",
        "qos": "",
        "retain": "",
        "respTopic": "",
        "contentType": "",
        "userProps": "",
        "correl": "",
        "expiry": "",
        "broker": "8f94c513d5abaf60",
        "x": 540,
        "y": 200,
        "wires": []
    },
    {
        "id": "3f5a03794dc8003b",
        "type": "mqtt out",
        "z": "eb1ca74049e20df8",
        "name": "",
        "topic": "2807hendiH",
        "qos": "",
        "retain": "",
        "respTopic": "",
        "contentType": "",
        "userProps": "",
        "correl": "",
        "expiry": "",
        "broker": "8f94c513d5abaf60",
        "x": 710,
        "y": 800,
        "wires": []
    },
    {
        "id": "bdcb4893238a0b51",
        "type": "mqtt out",
        "z": "eb1ca74049e20df8",
        "name": "",
        "topic": "2807hendiV",
        "qos": "",
        "retain": "",
        "respTopic": "",
        "contentType": "",
        "userProps": "",
        "correl": "",
        "expiry": "",
        "broker": "8f94c513d5abaf60",
        "x": 710,
        "y": 640,
        "wires": []
    },
    {
        "id": "907798b943552f8e",
        "type": "range",
        "z": "eb1ca74049e20df8",
        "minin": "-90",
        "maxin": "90",
        "minout": "-180",
        "maxout": "0",
        "action": "scale",
        "round": false,
        "property": "payload",
        "name": "",
        "x": 540,
        "y": 640,
        "wires": [
            [
                "bdcb4893238a0b51"
            ]
        ]
    },
    {
        "id": "b2e66230b14b4cf2",
        "type": "range",
        "z": "eb1ca74049e20df8",
        "minin": "-90",
        "maxin": "90",
        "minout": "0",
        "maxout": "180",
        "action": "scale",
        "round": false,
        "property": "payload",
        "name": "",
        "x": 540,
        "y": 800,
        "wires": [
            [
                "3f5a03794dc8003b"
            ]
        ]
    },
    {
        "id": "e346798d9843e113",
        "type": "debug",
        "z": "eb1ca74049e20df8",
        "name": "debug 4",
        "active": false,
        "tosidebar": true,
        "console": false,
        "tostatus": false,
        "complete": "false",
        "statusVal": "",
        "statusType": "auto",
        "x": 540,
        "y": 540,
        "wires": []
    },
    {
        "id": "1273fd4a572b3824",
        "type": "debug",
        "z": "eb1ca74049e20df8",
        "name": "debug 5",
        "active": false,
        "tosidebar": true,
        "console": false,
        "tostatus": false,
        "complete": "false",
        "statusVal": "",
        "statusType": "auto",
        "x": 540,
        "y": 720,
        "wires": []
    },
    {
        "id": "03ed9a3daffe04c4",
        "type": "mqtt out",
        "z": "eb1ca74049e20df8",
        "name": "",
        "topic": "Vasaljos/infared",
        "qos": "",
        "retain": "",
        "respTopic": "",
        "contentType": "",
        "userProps": "",
        "correl": "",
        "expiry": "",
        "broker": "8f94c513d5abaf60",
        "x": 540,
        "y": 480,
        "wires": []
    },
    {
        "id": "19bc145fca085268",
        "type": "mqtt out",
        "z": "eb1ca74049e20df8",
        "name": "",
        "topic": "Haus/augu_hradi",
        "qos": "",
        "retain": "",
        "respTopic": "",
        "contentType": "",
        "userProps": "",
        "correl": "",
        "expiry": "",
        "broker": "8f94c513d5abaf60",
        "x": 590,
        "y": 160,
        "wires": []
    },
    {
        "id": "dba943e48a7da7fd",
        "type": "ui_switch",
        "z": "eb1ca74049e20df8",
        "name": "",
        "label": "Spila hljóð",
        "tooltip": "",
        "group": "b26a1bbbf6f82626",
        "order": 1,
        "width": 0,
        "height": 0,
        "passthru": true,
        "decouple": "false",
        "topic": "topic",
        "topicType": "msg",
        "style": "",
        "onvalue": "true",
        "onvalueType": "bool",
        "onicon": "",
        "oncolor": "",
        "offvalue": "false",
        "offvalueType": "bool",
        "officon": "",
        "offcolor": "",
        "animate": false,
        "className": "",
        "x": 350,
        "y": 240,
        "wires": [
            [
                "065b84c9c0996259"
            ]
        ]
    },
    {
        "id": "469d1a3cc906d4ca",
        "type": "ui_switch",
        "z": "eb1ca74049e20df8",
        "name": "",
        "label": "Lýsa upp augun",
        "tooltip": "",
        "group": "b26a1bbbf6f82626",
        "order": 2,
        "width": 0,
        "height": 0,
        "passthru": true,
        "decouple": "false",
        "topic": "topic",
        "topicType": "msg",
        "style": "",
        "onvalue": "true",
        "onvalueType": "bool",
        "onicon": "",
        "oncolor": "",
        "offvalue": "false",
        "offvalueType": "bool",
        "officon": "",
        "offcolor": "",
        "animate": false,
        "className": "",
        "x": 360,
        "y": 200,
        "wires": [
            [
                "92d6fdc1ac7524fa"
            ]
        ]
    },
    {
        "id": "644e5aa77baaffeb",
        "type": "ui_switch",
        "z": "eb1ca74049e20df8",
        "name": "",
        "label": "Infared",
        "tooltip": "",
        "group": "4e193af265c1ef41",
        "order": 2,
        "width": 0,
        "height": 0,
        "passthru": true,
        "decouple": "false",
        "topic": "topic",
        "topicType": "msg",
        "style": "",
        "onvalue": "true",
        "onvalueType": "bool",
        "onicon": "",
        "oncolor": "",
        "offvalue": "false",
        "offvalueType": "bool",
        "officon": "",
        "offcolor": "",
        "animate": false,
        "className": "",
        "x": 340,
        "y": 480,
        "wires": [
            [
                "03ed9a3daffe04c4"
            ]
        ]
    },
    {
        "id": "e5a5afb657b5e022",
        "type": "ui_slider",
        "z": "eb1ca74049e20df8",
        "name": "",
        "label": "Hendi V",
        "tooltip": "",
        "group": "b26a1bbbf6f82626",
        "order": 3,
        "width": 0,
        "height": 0,
        "passthru": true,
        "outs": "all",
        "topic": "topic",
        "topicType": "msg",
        "min": "-90",
        "max": "90",
        "step": 1,
        "className": "",
        "x": 340,
        "y": 540,
        "wires": [
            [
                "89eb25052f2d924c",
                "e346798d9843e113"
            ]
        ]
    },
    {
        "id": "cc9cd820b26528ac",
        "type": "ui_slider",
        "z": "eb1ca74049e20df8",
        "name": "",
        "label": "Hendi H",
        "tooltip": "",
        "group": "b26a1bbbf6f82626",
        "order": 5,
        "width": 0,
        "height": 0,
        "passthru": true,
        "outs": "all",
        "topic": "topic",
        "topicType": "msg",
        "min": "-90",
        "max": "90",
        "step": 1,
        "className": "",
        "x": 340,
        "y": 720,
        "wires": [
            [
                "1273fd4a572b3824",
                "12aa149ee5dff7c3"
            ]
        ]
    },
    {
        "id": "708dab602582a5ad",
        "type": "ui_slider",
        "z": "eb1ca74049e20df8",
        "name": "",
        "label": "Blikkhraði augna",
        "tooltip": "",
        "group": "b26a1bbbf6f82626",
        "order": 7,
        "width": 0,
        "height": 0,
        "passthru": true,
        "outs": "all",
        "topic": "topic",
        "topicType": "msg",
        "min": 0,
        "max": 10,
        "step": 1,
        "className": "",
        "x": 370,
        "y": 160,
        "wires": [
            [
                "19bc145fca085268"
            ]
        ]
    },
    {
        "id": "12aa149ee5dff7c3",
        "type": "ui_numeric",
        "z": "eb1ca74049e20df8",
        "name": "",
        "label": "numeric H",
        "tooltip": "",
        "group": "b26a1bbbf6f82626",
        "order": 6,
        "width": 0,
        "height": 0,
        "wrap": false,
        "passthru": true,
        "topic": "topic",
        "topicType": "msg",
        "format": "{{value}}",
        "min": "-90",
        "max": "90",
        "step": 1,
        "className": "",
        "x": 350,
        "y": 800,
        "wires": [
            [
                "b2e66230b14b4cf2"
            ]
        ]
    },
    {
        "id": "89eb25052f2d924c",
        "type": "ui_numeric",
        "z": "eb1ca74049e20df8",
        "name": "",
        "label": "numeric V",
        "tooltip": "",
        "group": "b26a1bbbf6f82626",
        "order": 4,
        "width": 0,
        "height": 0,
        "wrap": false,
        "passthru": true,
        "topic": "topic",
        "topicType": "msg",
        "format": "{{value}}",
        "min": "-90",
        "max": "90",
        "step": 1,
        "className": "",
        "x": 340,
        "y": 640,
        "wires": [
            [
                "907798b943552f8e"
            ]
        ]
    },
    {
        "id": "7a594254f669494e",
        "type": "ui_colour_picker",
        "z": "eb1ca74049e20df8",
        "name": "",
        "label": "Litur á vasaljósi",
        "group": "4e193af265c1ef41",
        "format": "rgb",
        "outformat": "string",
        "showSwatch": true,
        "showPicker": false,
        "showValue": false,
        "showHue": false,
        "showAlpha": false,
        "showLightness": true,
        "square": "false",
        "dynOutput": "false",
        "order": 1,
        "width": "0",
        "height": "0",
        "passthru": true,
        "topic": "topic",
        "topicType": "msg",
        "className": "",
        "x": 360,
        "y": 280,
        "wires": [
            [
                "be0453c56bb42545"
            ]
        ]
    },
    {
        "id": "a53e13d82a657c1e",
        "type": "mqtt out",
        "z": "eb1ca74049e20df8",
        "name": "",
        "topic": "Vasaljos/motor_hradi",
        "qos": "",
        "retain": "",
        "respTopic": "",
        "contentType": "",
        "userProps": "",
        "correl": "",
        "expiry": "",
        "broker": "8f94c513d5abaf60",
        "x": 580,
        "y": 880,
        "wires": []
    },
    {
        "id": "b6eef3562063b484",
        "type": "ui_slider",
        "z": "eb1ca74049e20df8",
        "name": "",
        "label": "Mótor Hraði",
        "tooltip": "",
        "group": "4e193af265c1ef41",
        "order": 8,
        "width": 0,
        "height": 0,
        "passthru": true,
        "outs": "all",
        "topic": "topic",
        "topicType": "msg",
        "min": "0",
        "max": "1023",
        "step": 1,
        "className": "",
        "x": 370,
        "y": 880,
        "wires": [
            [
                "a53e13d82a657c1e",
                "0a672e2c1ac1daf5",
                "ed2b4d43c2f4eae5"
            ]
        ]
    },
    {
        "id": "0a672e2c1ac1daf5",
        "type": "ui_text",
        "z": "eb1ca74049e20df8",
        "group": "4e193af265c1ef41",
        "order": 3,
        "width": 0,
        "height": 0,
        "name": "",
        "label": "Mótorhraði",
        "format": "{{msg.payload}}",
        "layout": "row-spread",
        "className": "",
        "style": false,
        "font": "",
        "fontSize": 16,
        "color": "#000000",
        "x": 550,
        "y": 940,
        "wires": []
    },
    {
        "id": "ed2b4d43c2f4eae5",
        "type": "ui-text",
        "z": "eb1ca74049e20df8",
        "group": "ad4b3c1b85a734e9",
        "order": 1,
        "width": 0,
        "height": 0,
        "name": "",
        "label": "text",
        "format": "{{msg.payload}}",
        "layout": "row-spread",
        "style": false,
        "font": "",
        "fontSize": 16,
        "color": "#717171",
        "wrapText": false,
        "className": "",
        "x": 530,
        "y": 980,
        "wires": []
    },
    {
        "id": "18dc71686f146f9e",
        "type": "ui_slider",
        "z": "eb1ca74049e20df8",
        "name": "",
        "label": "Birtustig Ljósa",
        "tooltip": "",
        "group": "4e193af265c1ef41",
        "order": 8,
        "width": 0,
        "height": 0,
        "passthru": true,
        "outs": "all",
        "topic": "topic",
        "topicType": "msg",
        "min": "-1",
        "max": "0",
        "step": "0.01",
        "className": "",
        "x": 360,
        "y": 320,
        "wires": [
            [
                "d27e392795c950a4"
            ]
        ]
    },
    {
        "id": "d27e392795c950a4",
        "type": "mqtt out",
        "z": "eb1ca74049e20df8",
        "name": "",
        "topic": "Vasaljos/birta",
        "qos": "",
        "retain": "",
        "respTopic": "",
        "contentType": "",
        "userProps": "",
        "correl": "",
        "expiry": "",
        "broker": "8f94c513d5abaf60",
        "x": 550,
        "y": 320,
        "wires": []
    },
    {
        "id": "ebd55a05e70aab20",
        "type": "ui_slider",
        "z": "eb1ca74049e20df8",
        "name": "",
        "label": "Kjálki",
        "tooltip": "",
        "group": "b26a1bbbf6f82626",
        "order": 14,
        "width": 0,
        "height": 0,
        "passthru": true,
        "outs": "all",
        "topic": "topic",
        "topicType": "msg",
        "min": "28",
        "max": "62",
        "step": 1,
        "className": "",
        "x": 330,
        "y": 360,
        "wires": [
            [
                "7d6ce716b9720dac",
                "7bd635d4ae4646e3"
            ]
        ]
    },
    {
        "id": "7d6ce716b9720dac",
        "type": "mqtt out",
        "z": "eb1ca74049e20df8",
        "name": "",
        "topic": "Haus/kjalki",
        "qos": "",
        "retain": "",
        "respTopic": "",
        "contentType": "",
        "userProps": "",
        "correl": "",
        "expiry": "",
        "broker": "8f94c513d5abaf60",
        "x": 530,
        "y": 360,
        "wires": []
    },
    {
        "id": "7bd635d4ae4646e3",
        "type": "ui_numeric",
        "z": "eb1ca74049e20df8",
        "name": "",
        "label": "numeric K",
        "tooltip": "",
        "group": "b26a1bbbf6f82626",
        "order": 15,
        "width": 0,
        "height": 0,
        "wrap": false,
        "passthru": true,
        "topic": "topic",
        "topicType": "msg",
        "format": "{{value}}",
        "min": 0,
        "max": 10,
        "step": 1,
        "className": "",
        "x": 520,
        "y": 420,
        "wires": [
            []
        ]
    },
    {
        "id": "a15f6c5faa21f1b5",
        "type": "ui_slider",
        "z": "eb1ca74049e20df8",
        "name": "",
        "label": "Líkami",
        "tooltip": "",
        "group": "b26a1bbbf6f82626",
        "order": 14,
        "width": 0,
        "height": 0,
        "passthru": true,
        "outs": "all",
        "topic": "topic",
        "topicType": "msg",
        "min": "28",
        "max": "62",
        "step": 1,
        "className": "",
        "x": 770,
        "y": 360,
        "wires": [
            [
                "840075a47e91eb2f",
                "820c8f1c45c85518"
            ]
        ]
    },
    {
        "id": "840075a47e91eb2f",
        "type": "mqtt out",
        "z": "eb1ca74049e20df8",
        "name": "",
        "topic": "Haus/likami",
        "qos": "",
        "retain": "",
        "respTopic": "",
        "contentType": "",
        "userProps": "",
        "correl": "",
        "expiry": "",
        "broker": "8f94c513d5abaf60",
        "x": 970,
        "y": 360,
        "wires": []
    },
    {
        "id": "820c8f1c45c85518",
        "type": "ui_numeric",
        "z": "eb1ca74049e20df8",
        "name": "",
        "label": "numeric L",
        "tooltip": "",
        "group": "b26a1bbbf6f82626",
        "order": 15,
        "width": 0,
        "height": 0,
        "wrap": false,
        "passthru": true,
        "topic": "topic",
        "topicType": "msg",
        "format": "{{value}}",
        "min": 0,
        "max": 10,
        "step": 1,
        "className": "",
        "x": 960,
        "y": 420,
        "wires": [
            []
        ]
    },
    {
        "id": "90f91359612e8980",
        "type": "ui_slider",
        "z": "eb1ca74049e20df8",
        "name": "",
        "label": "Háls Lárétt",
        "tooltip": "",
        "group": "b26a1bbbf6f82626",
        "order": 14,
        "width": 0,
        "height": 0,
        "passthru": true,
        "outs": "all",
        "topic": "topic",
        "topicType": "msg",
        "min": "30",
        "max": "130",
        "step": 1,
        "className": "",
        "x": 790,
        "y": 160,
        "wires": [
            [
                "158ad74ac19e1471",
                "9347481deeb3cf81"
            ]
        ]
    },
    {
        "id": "158ad74ac19e1471",
        "type": "mqtt out",
        "z": "eb1ca74049e20df8",
        "name": "",
        "topic": "Haus/halslarett",
        "qos": "",
        "retain": "",
        "respTopic": "",
        "contentType": "",
        "userProps": "",
        "correl": "",
        "expiry": "",
        "broker": "8f94c513d5abaf60",
        "x": 980,
        "y": 160,
        "wires": []
    },
    {
        "id": "9347481deeb3cf81",
        "type": "ui_numeric",
        "z": "eb1ca74049e20df8",
        "name": "",
        "label": "numeric Háls_lárétt",
        "tooltip": "",
        "group": "b26a1bbbf6f82626",
        "order": 15,
        "width": 0,
        "height": 0,
        "wrap": false,
        "passthru": true,
        "topic": "topic",
        "topicType": "msg",
        "format": "{{value}}",
        "min": 0,
        "max": 10,
        "step": 1,
        "className": "",
        "x": 990,
        "y": 220,
        "wires": [
            []
        ]
    },
    {
        "id": "6d78791297d834a2",
        "type": "ui_slider",
        "z": "eb1ca74049e20df8",
        "name": "",
        "label": "Háls Lóðrétt",
        "tooltip": "",
        "group": "b26a1bbbf6f82626",
        "order": 14,
        "width": 0,
        "height": 0,
        "passthru": true,
        "outs": "all",
        "topic": "topic",
        "topicType": "msg",
        "min": "0",
        "max": "62",
        "step": 1,
        "className": "",
        "x": 790,
        "y": 260,
        "wires": [
            [
                "7863fab7fec033c9",
                "cca74684a1ab8217"
            ]
        ]
    },
    {
        "id": "7863fab7fec033c9",
        "type": "mqtt out",
        "z": "eb1ca74049e20df8",
        "name": "",
        "topic": "Haus/halslodrett",
        "qos": "",
        "retain": "",
        "respTopic": "",
        "contentType": "",
        "userProps": "",
        "correl": "",
        "expiry": "",
        "broker": "8f94c513d5abaf60",
        "x": 980,
        "y": 260,
        "wires": []
    },
    {
        "id": "cca74684a1ab8217",
        "type": "ui_numeric",
        "z": "eb1ca74049e20df8",
        "name": "",
        "label": "numeric Háls_lóðrétt",
        "tooltip": "",
        "group": "b26a1bbbf6f82626",
        "order": 15,
        "width": 0,
        "height": 0,
        "wrap": false,
        "passthru": true,
        "topic": "topic",
        "topicType": "msg",
        "format": "{{value}}",
        "min": 0,
        "max": 10,
        "step": 1,
        "className": "",
        "x": 1000,
        "y": 320,
        "wires": [
            []
        ]
    },
    {
        "id": "e8440ab49b4f872a",
        "type": "mqtt in",
        "z": "eb1ca74049e20df8",
        "name": "",
        "topic": "Vasaljos/scena",
        "qos": "2",
        "datatype": "auto-detect",
        "broker": "8f94c513d5abaf60",
        "nl": false,
        "rap": true,
        "rh": 0,
        "inputs": 0,
        "x": 740,
        "y": 540,
        "wires": [
            [
                "c9f288d0a511e1ef"
            ]
        ]
    },
    {
        "id": "c9f288d0a511e1ef",
        "type": "switch",
        "z": "eb1ca74049e20df8",
        "name": "",
        "property": "payload",
        "propertyType": "msg",
        "rules": [
            {
                "t": "eq",
                "v": "0",
                "vt": "num"
            },
            {
                "t": "eq",
                "v": "1",
                "vt": "num"
            }
        ],
        "checkall": "true",
        "repair": false,
        "outputs": 2,
        "x": 910,
        "y": 540,
        "wires": [
            [
                "bff113487b0774eb"
            ],
            [
                "d272680951f54d5a"
            ]
        ]
    },
    {
        "id": "bff113487b0774eb",
        "type": "mqtt out",
        "z": "eb1ca74049e20df8",
        "name": "Enda scenu",
        "topic": "Vasaljos/infared",
        "qos": "",
        "retain": "",
        "respTopic": "",
        "contentType": "",
        "userProps": "",
        "correl": "",
        "expiry": "",
        "broker": "8f94c513d5abaf60",
        "x": 1070,
        "y": 500,
        "wires": []
    },
    {
        "id": "d272680951f54d5a",
        "type": "mqtt out",
        "z": "eb1ca74049e20df8",
        "name": "Byrja scenu",
        "topic": "Vasaljos/infared",
        "qos": "",
        "retain": "",
        "respTopic": "",
        "contentType": "",
        "userProps": "",
        "correl": "",
        "expiry": "",
        "broker": "8f94c513d5abaf60",
        "x": 1070,
        "y": 580,
        "wires": []
    },
    {
        "id": "8f94c513d5abaf60",
        "type": "mqtt-broker",
        "name": "Raspberry Pi",
        "broker": "localhost",
        "port": "1883",
        "clientid": "",
        "autoConnect": true,
        "usetls": false,
        "protocolVersion": "4",
        "keepalive": "60",
        "cleansession": true,
        "autoUnsubscribe": true,
        "birthTopic": "",
        "birthQos": "0",
        "birthRetain": "false",
        "birthPayload": "",
        "birthMsg": {},
        "closeTopic": "",
        "closeQos": "0",
        "closeRetain": "false",
        "closePayload": "",
        "closeMsg": {},
        "willTopic": "",
        "willQos": "0",
        "willRetain": "false",
        "willPayload": "",
        "willMsg": {},
        "userProps": "",
        "sessionExpiry": ""
    },
    {
        "id": "b26a1bbbf6f82626",
        "type": "ui_group",
        "name": "Hauskúpa",
        "tab": "07bc3cb419400183",
        "order": 1,
        "disp": true,
        "width": "6",
        "collapse": false,
        "className": ""
    },
    {
        "id": "4e193af265c1ef41",
        "type": "ui_group",
        "name": "Vasaljós",
        "tab": "07bc3cb419400183",
        "order": 2,
        "disp": true,
        "width": "6",
        "collapse": false,
        "className": ""
    },
    {
        "id": "ad4b3c1b85a734e9",
        "type": "ui-group",
        "name": "Vasaljós",
        "page": "a87f025a397f8200",
        "width": "6",
        "height": "1",
        "order": 2,
        "showTitle": true,
        "className": "",
        "visible": "true",
        "disabled": "false",
        "groupType": "default"
    },
    {
        "id": "07bc3cb419400183",
        "type": "ui_tab",
        "name": "Lokaverkefni",
        "icon": "dashboard",
        "order": 1,
        "disabled": false,
        "hidden": false
    },
    {
        "id": "a87f025a397f8200",
        "type": "ui-page",
        "name": "Lokaverkefni",
        "ui": "784b0f7602e9f726",
        "path": "/page1",
        "icon": "home",
        "layout": "grid",
        "theme": "ab4937a2d52683b9",
        "breakpoints": [
            {
                "name": "Default",
                "px": "0",
                "cols": "3"
            },
            {
                "name": "Tablet",
                "px": "576",
                "cols": "6"
            },
            {
                "name": "Small Desktop",
                "px": "768",
                "cols": "9"
            },
            {
                "name": "Desktop",
                "px": "1024",
                "cols": "12"
            }
        ],
        "order": 1,
        "className": "",
        "visible": "true",
        "disabled": "false"
    },
    {
        "id": "784b0f7602e9f726",
        "type": "ui-base",
        "name": "My Dashboard",
        "path": "/dashboard",
        "appIcon": "",
        "includeClientData": true,
        "acceptsClientConfig": [
            "ui-notification",
            "ui-control"
        ],
        "showPathInSidebar": false,
        "showPageTitle": true,
        "navigationStyle": "default",
        "titleBarStyle": "default"
    },
    {
        "id": "ab4937a2d52683b9",
        "type": "ui-theme",
        "name": "Default Theme",
        "colors": {
            "surface": "#ffffff",
            "primary": "#0094CE",
            "bgPage": "#eeeeee",
            "groupBg": "#ffffff",
            "groupOutline": "#cccccc"
        },
        "sizes": {
            "density": "default",
            "pagePadding": "12px",
            "groupGap": "12px",
            "groupBorderRadius": "4px",
            "widgetGap": "12px"
        }
    }
]